cli/__init__.py
cli/main.py
command/__init__.py
command/check.py
command/delete.py
command/read.py
command/send.py
command/util/__init__.py
command/util/serial_stream.py
sms_cli-1.0.4.dist-info/LICENSE.md
sms_cli-1.0.4.dist-info/METADATA
sms_cli-1.0.4.dist-info/WHEEL
sms_cli-1.0.4.dist-info/entry_points.txt
sms_cli-1.0.4.dist-info/top_level.txt
sms_cli-1.0.4.dist-info/RECORD
