Metadata-Version: 2.1
Name: sms-cli
Version: 1.0.4
Summary: Command-line interface for sending AT (ATtention) commands via serial port to GSM shield module.
Home-page: https://github.com/lmatosevic/sms-cli
Download-URL: https://github.com/lmatosevic/sms-cli/archive/refs/tags/1.0.4.tar.gz
Author: luka
Author-email: lukamatosevic5@gmail.com
Keywords: sms,cli,messaging,gsm
Requires-Python: >=3.6
License-File: LICENSE.md
Requires-Dist: pyserial
Requires-Dist: argparse
